README.md
README.rst
setup.py
i2FHIRb2.egg-info/PKG-INFO
i2FHIRb2.egg-info/SOURCES.txt
i2FHIRb2.egg-info/dependency_links.txt
i2FHIRb2.egg-info/requires.txt
i2FHIRb2.egg-info/top_level.txt
i2fhirb2/__init__.py
i2fhirb2/common_cli_parameters.py
i2fhirb2/conf_file.py
i2fhirb2/generate_i2b2.py
i2fhirb2/loadfacts.py
i2fhirb2/removefacts.py
i2fhirb2/fhir/__init__.py
i2fhirb2/fhir/fhircodemapping.py
i2fhirb2/fhir/fhirconceptdimension.py
i2fhirb2/fhir/fhirdimensionmetadata.py
i2fhirb2/fhir/fhirencountermapping.py
i2fhirb2/fhir/fhirmetadatavocabulary.py
i2fhirb2/fhir/fhirmodifierdimension.py
i2fhirb2/fhir/fhirnamespaces.py
i2fhirb2/fhir/fhirobservationfact.py
i2fhirb2/fhir/fhirontology.py
i2fhirb2/fhir/fhirontologytable.py
i2fhirb2/fhir/fhirpatientdimension.py
i2fhirb2/fhir/fhirpatientmapping.py
i2fhirb2/fhir/fhirprimitivetypes.py
i2fhirb2/fhir/fhirproviderdimension.py
i2fhirb2/fhir/fhirresourcemap.py
i2fhirb2/fhir/fhirspecific.py
i2fhirb2/fhir/fhirvisitdimension.py
i2fhirb2/fhir/fhirw5ontology.py
i2fhirb2/loaders/__init__.py
i2fhirb2/loaders/i2b2graphmap.py
i2fhirb2/tsv_support/__init__.py
i2fhirb2/tsv_support/tsvwriter.py
scripts/__init__.py
scripts/conf_file
scripts/generate_i2b2
scripts/loadfacts
scripts/removefacts
tests/__init__.py