Metadata-Version: 1.1
Name: i2FHIRb2
Version: 0.4.1
Summary: FHIR in i2b2 model conversion tools
Home-page: https://github.com/BD2KOnFHIR/i2FHIRb2
Author: Harold Solbrig
Author-email: solbrig.harold@mayo.edu
License: Apache 2.0
Platform: UNKNOWN
Classifier: Development Status :: 3 - Alpha
Classifier: Environment :: Console
Classifier: Intended Audience :: Healthcare Industry
Classifier: License :: OSI Approved :: Apache Software License
Classifier: Topic :: Database
Classifier: Programming Language :: Python :: 3.6
